por/scraper.py
por/sphinx_extensions/__init__.py
por/sphinx_extensions/processor/html_translator.py
por/sphinx_extensions/processor/parser.py
por/sphinx_extensions/processor/roles.py
por/sphinx_extensions/processor/transforms/contents.py
por/sphinx_extensions/processor/transforms/title.py
por-0.1.2.dist-info/LICENSE
por-0.1.2.dist-info/METADATA
por-0.1.2.dist-info/WHEEL
por-0.1.2.dist-info/top_level.txt
por-0.1.2.dist-info/RECORD
