Metadata-Version: 2.1
Name: por
Version: 0.1.2
Summary: The unofficial programmatic POR
Home-page: https://github.com/the-scouts/por
Author: Adam Turner
License: MIT
Keywords: standards,semantic,scouts
Platform: any
Classifier: Development Status :: 3 - Alpha
Classifier: Intended Audience :: Developers
Classifier: License :: OSI Approved :: MIT License
Classifier: Operating System :: OS Independent
Classifier: Programming Language :: Python :: 3 :: Only
Classifier: Programming Language :: Python :: 3.9
Classifier: Programming Language :: Python :: Implementation :: CPython
Classifier: Programming Language :: Python :: Implementation :: PyPy
Classifier: Topic :: Software Development
Classifier: Topic :: Utilities
Requires-Python: >=3.9
License-File: LICENSE
Requires-Dist: requests
Requires-Dist: docutils
Requires-Dist: Sphinx
